deepseek_ocr_ollama/__init__.py
deepseek_ocr_ollama/__main__.py
deepseek_ocr_ollama/ref.py
deepseek_ocr_ollama-1.3.dist-info/METADATA
deepseek_ocr_ollama-1.3.dist-info/WHEEL
deepseek_ocr_ollama-1.3.dist-info/entry_points.txt
deepseek_ocr_ollama-1.3.dist-info/top_level.txt
deepseek_ocr_ollama-1.3.dist-info/RECORD
