Metadata-Version: 2.4
Name: deepseek-ocr-ollama
Version: 1.3
Summary: A simple script that uses the Ollama API to get the Markdown text from a PDF or image file using the DeepSeek-OCR model
Home-page: https://github.com/jfhack/deepseek-ocr-ollama
Requires-Dist: ollama
Requires-Dist: pymupdf
Requires-Dist: python-dotenv
Requires-Dist: tqdm
Requires-Dist: pillow
Dynamic: description
Dynamic: description-content-type
Dynamic: home-page
Dynamic: requires-dist
Dynamic: summary
